log95/__init__.py
log95-1.3.dist-info/licenses/LICENCE
log95-1.3.dist-info/METADATA
log95-1.3.dist-info/WHEEL
log95-1.3.dist-info/top_level.txt
log95-1.3.dist-info/RECORD
