Metadata-Version: 2.4
Name: log95
Version: 1.3
Summary: Simple logger
Home-page: https://gitlab.com/KubaPro010/log95
Author: kuba201
Project-URL: Source, https://gitlab.com/KubaPro010/log95
Classifier: Programming Language :: Python :: 3 :: Only
Classifier: Programming Language :: Python :: 3.10
Classifier: Development Status :: 5 - Production/Stable
License-File: LICENCE
Requires-Dist: colorama
Dynamic: author
Dynamic: classifier
Dynamic: description
Dynamic: description-content-type
Dynamic: home-page
Dynamic: license-file
Dynamic: project-url
Dynamic: requires-dist
Dynamic: summary
